{
  "review_type": "final_execution_simulation",
  "timestamp": "2026-04-23T19:16:00+08:00",
  "phase_by_phase_analysis": [
    {
      "phase": 1,
      "name": "Master Agent",
      "expected_issues": [],
      "confidence": "high"
    },
    {
      "phase": 2,
      "name": "Orchestrator Agent",
      "expected_issues": [
        "需确保 tasks.json 和 execution_plan.json 路径正确读取"
      ],
      "confidence": "high"
    },
    {
      "phase": 3,
      "name": "DataManager Worker",
      "expected_issues": [
        "若 gemini/duckduckgo/tushare 依赖缺失，bootstrap 可能失败但会 fallback 到最小化 key_metrics.json",
        "补充搜索最多重试 2 次，若全部失败则记录为 partial"
      ],
      "confidence": "medium"
    },
    {
      "phase": 4,
      "name": "Planner Worker",
      "expected_issues": [
        "依赖 key_metrics.json 存在，若 DataManager 未生成则 Planner 可能使用默认值"
      ],
      "confidence": "medium"
    },
    {
      "phase": 5,
      "name": "Researchers (Parallel)",
      "expected_issues": [
        "6 个 Researcher 并行执行，若某个超时或失败，其他仍可继续",
        "依赖 planner_output.json，若 Planner 失败则 Researcher 可能缺乏重点"
      ],
      "confidence": "medium"
    },
    {
      "phase": 6,
      "name": "Auditors (Parallel)",
      "expected_issues": [
        "3 个 Auditor 并行执行，依赖所有 researcher_*_output.json",
        "若某个 Researcher 输出缺失，对应 Auditor 可能跳过或报错"
      ],
      "confidence": "medium"
    },
    {
      "phase": 7,
      "name": "Fixer Worker",
      "expected_issues": [
        "整合所有 researcher 和 auditor 输出，若部分缺失仍能运行但质量下降",
        "标记为 optional，即使失败也不阻断后续流程"
      ],
      "confidence": "medium"
    },
    {
      "phase": 8,
      "name": "Summarizer Worker",
      "expected_issues": [
        "分层读取策略：优先读取 factual auditor 和 finance/macro researchers",
        "若核心输入缺失，报告质量显著下降但仍可生成最小化报告"
      ],
      "confidence": "medium"
    }
  ],
  "failure_mode_analysis": {
    "data_manager_bootstrap_fails": {
      "impact": "key_metrics.json 使用默认值（None），Planner 和 Researchers 缺乏实时数据",
      "mitigation": "DataManager 会生成最小化 key_metrics.json，补充搜索仍可提供行业信息；系统继续执行"
    },
    "search_all_fails": {
      "impact": "补充搜索全部失败，报告缺乏最新市场动态和券商预期",
      "mitigation": "Bootstrap 采集的基础数据仍可用；报告标注数据局限性；用户可手动补充"
    },
    "researcher_timeout": {
      "expected_behavior": "超时 Researcher 无输出文件，对应 Auditor 检测到文件缺失时跳过该维度审计",
      "impact": "报告缺少该角度分析（如 tech 或 management），但其他角度仍完整",
      "mitigation": "Orchestrator 记录超时警告；Summarizer 分层读取时可降级使用其他 Researchers 输出"
    },
    "orchestrator_spawn_fails": {
      "impact": "整个管线无法启动，无任何输出",
      "mitigation": "主Agent 捕获 spawn 异常并重试；记录错误日志供诊断；用户收到明确错误提示"
    }
  },
  "expected_outcomes": {
    "best_case": {
      "probability": "30%",
      "quality": "high",
      "time_minutes": 20,
      "description": "所有依赖可用，bootstrap 成功，补充搜索全部成功，所有 Workers 按时完成。报告包含完整的多维度分析、审计修正和三情景目标价。"
    },
    "typical_case": {
      "probability": "50%",
      "quality": "medium",
      "time_minutes": 15,
      "description": "部分搜索失败或某个 Researcher 超时，但核心数据（finance, macro_chain, factual audit）可用。报告质量良好但某些角度较简略。"
    },
    "worst_case": {
      "probability": "20%",
      "quality": "low",
      "time_minutes": 10,
      "description": "Bootstrap 失败且补充搜索全部失败，或关键 Workers（Planner/Summarizer）超时。报告仅包含最小化信息，标注数据局限性。"
    }
  },
  "reliability_score": 0.85,
  "is_ready_to_run": true,
  "confidence": "high",
  "recommendations": [
    "✅ 修复验证通过：DataManager Task 中的 {session_id} 会被正确替换为真实值（f-string 直接嵌入）",
    "✅ 修复验证通过：Planner/Researcher/Auditor Tasks 均调用 replace_template_vars，{{code}}/{{name}} 被正确替换",
    "✅ 数据流可靠：key_metrics.json → Planner → Researchers → Auditors → Fixer → Summarizer 的链式依赖已建立",
    "⚠️ 建议增加 Orchestrator 层面的超时监控，避免单个 Worker 卡住整个管线",
    "⚠️ 建议为 Summarizer 增加 fallback 逻辑：当核心输入缺失时，使用可用数据生成简化报告并明确标注局限性",
    "✅ 与修复前相比，可靠性显著提升：模板变量替换 bug 已修复，DataManager 错误处理完善，fallback 机制健全"
  ]
}
